Metadata-Version: 2.1
Name: pytrading212api
Version: 2026.1.1
Summary: Trading 212 api wrapper
Home-page: https://github.com/ryanbdclark/pytrading212api
Author: Ryan Clark
Keywords: trading,212,api,trading212
Classifier: License :: OSI Approved :: MIT License
Classifier: Programming Language :: Python :: 3.10
Requires-Python: >=3.10
Requires-Dist: aiohttp
